odoo/addons/account_payment_order_grouped_output/README.rst
odoo/addons/account_payment_order_grouped_output/__init__.py
odoo/addons/account_payment_order_grouped_output/__manifest__.py
odoo/addons/account_payment_order_grouped_output/i18n/account_payment_order_grouped_output.pot
odoo/addons/account_payment_order_grouped_output/i18n/es.po
odoo/addons/account_payment_order_grouped_output/i18n/fr.po
odoo/addons/account_payment_order_grouped_output/models/__init__.py
odoo/addons/account_payment_order_grouped_output/models/account_move.py
odoo/addons/account_payment_order_grouped_output/models/account_payment_mode.py
odoo/addons/account_payment_order_grouped_output/models/account_payment_order.py
odoo/addons/account_payment_order_grouped_output/readme/DESCRIPTION.rst
odoo/addons/account_payment_order_grouped_output/static/description/icon.png
odoo/addons/account_payment_order_grouped_output/static/description/index.html
odoo/addons/account_payment_order_grouped_output/tests/__init__.py
odoo/addons/account_payment_order_grouped_output/tests/test_payment_order_inbound_grouped.py
odoo/addons/account_payment_order_grouped_output/views/account_payment_mode_views.xml
odoo/addons/account_payment_order_grouped_output/views/account_payment_order_views.xml
odoo14_addon_account_payment_order_grouped_output-14.0.1.0.2.dist-info/METADATA
odoo14_addon_account_payment_order_grouped_output-14.0.1.0.2.dist-info/WHEEL
odoo14_addon_account_payment_order_grouped_output-14.0.1.0.2.dist-info/top_level.txt
odoo14_addon_account_payment_order_grouped_output-14.0.1.0.2.dist-info/RECORD
