Metadata-Version: 2.1
Name: odoo14-addon-account_payment_order_grouped_output
Version: 14.0.1.0.2
Summary: Account Payment Order - Generate grouped moves
Home-page: https://github.com/OCA/bank-payment
Author: ACSONE SA/NV, Therp BV, Tecnativa, Akretion, Odoo Community Association (OCA)
Author-email: support@odoo-community.org
License: AGPL-3
Classifier: Programming Language :: Python
Classifier: Framework :: Odoo
Classifier: Framework :: Odoo :: 14.0
Classifier: License :: OSI Approved :: GNU Affero General Public License v3
Requires-Python: >=3.6
Requires-Dist: odoo14-addon-account-payment-order
Requires-Dist: odoo <14.1dev,>=14.0a
